proxy_reader/__init__.py
proxy_reader/_types.py
proxy_reader/domains.py
proxy_reader/logs_config.py
proxy_reader/proxy.py
proxy_reader/py.typed
proxy_reader/reader.py
proxy_reader/utils.py
proxy_reader/protocols/__init__.py
proxy_reader/protocols/reader.py
proxy_reader-2.1.2.dist-info/licenses/LICENSE
proxy_reader-2.1.2.dist-info/METADATA
proxy_reader-2.1.2.dist-info/WHEEL
proxy_reader-2.1.2.dist-info/top_level.txt
proxy_reader-2.1.2.dist-info/RECORD
