Metadata-Version: 2.4
Name: proxy-reader
Version: 2.1.2
Summary: Proxy reader for Python
Project-URL: Homepage, https://github.com/runetech0/proxy-reader
Project-URL: github, https://github.com/runetech0/proxy-reader
Requires-Python: >=3.12
License-File: LICENSE
Requires-Dist: aiohttp>=3.12.15
Requires-Dist: aiohttp-socks>=0.9.0
Requires-Dist: pytest>=8.4.1
Provides-Extra: test
Requires-Dist: pytest>=7.0.0; extra == "test"
Dynamic: license-file
